ewsnmap/__init__.py
ewsnmap/ewsnmap.py
ews_nmap-1.0.4.dist-info/entry_points.txt
ews_nmap-1.0.4.dist-info/LICENSE
ews_nmap-1.0.4.dist-info/WHEEL
ews_nmap-1.0.4.dist-info/METADATA
ews_nmap-1.0.4.dist-info/RECORD
