Metadata-Version: 2.1
Name: ews-nmap
Version: 1.0.4
Summary: Extract web servers from an Nmap XML file
License: LICENSE
Author: SecSI
Author-email: dev@secsi.io
Requires-Python: >=3.8,<4.0
Classifier: License :: Other/Proprietary License
Classifier: Programming Language :: Python :: 3
Classifier: Programming Language :: Python :: 3.8
Classifier: Programming Language :: Python :: 3.9
Classifier: Programming Language :: Python :: 3.10
Classifier: Programming Language :: Python :: 3.11
Requires-Dist: fire (>=0.4.0,<0.5.0)
Requires-Dist: python-libnmap (>=0.7.3,<0.8.0)
